recipe_decrapinator/decrapinator.py
recipe_decrapinator/schemas/www.allrecipes.com.json
recipe_decrapinator-0.0.7.dist-info/LICENSE
recipe_decrapinator-0.0.7.dist-info/METADATA
recipe_decrapinator-0.0.7.dist-info/WHEEL
recipe_decrapinator-0.0.7.dist-info/top_level.txt
recipe_decrapinator-0.0.7.dist-info/RECORD
